[
    {
        "key": "dbln",
        "value": "%7B%2261576873704000%22%3A%228muoKyaF%22%2C%2261579860272280%22%3A%22BIEgns31%22%7D",
        "domain": "facebook.com",
        "path": "/login/device-based/",
        "hostOnly": false,
        "creation": "2025-08-29T10:48:30.000Z",
        "lastAccessed": "2025-08-29T10:48:30.000Z"
    },
    {
        "key": "datr",
        "value": "kL6paMUwmePCUhioJyIM3fD4",
        "domain": "facebook.com",
        "path": "/",
        "hostOnly": false,
        "creation": "2025-08-29T10:48:30.000Z",
        "lastAccessed": "2025-08-29T10:48:30.000Z"
    },
    {
        "key": "sb",
        "value": "kL6paBma7cIp-3a543VP5hMM",
        "domain": "facebook.com",
        "path": "/",
        "hostOnly": false,
        "creation": "2025-08-29T10:48:30.000Z",
        "lastAccessed": "2025-08-29T10:48:30.000Z"
    },
    {
        "key": "vpd",
        "value": "v1%3B767x393x2.75",
        "domain": "facebook.com",
        "path": "/",
        "hostOnly": false,
        "creation": "2025-08-29T10:48:30.000Z",
        "lastAccessed": "2025-08-29T10:48:30.000Z"
    },
    {
        "key": "ps_l",
        "value": "1",
        "domain": "facebook.com",
        "path": "/",
        "hostOnly": false,
        "creation": "2025-08-29T10:48:30.000Z",
        "lastAccessed": "2025-08-29T10:48:30.000Z"
    },
    {
        "key": "ps_n",
        "value": "1",
        "domain": "facebook.com",
        "path": "/",
        "hostOnly": false,
        "creation": "2025-08-29T10:48:30.000Z",
        "lastAccessed": "2025-08-29T10:48:30.000Z"
    },
    {
        "key": "pas",
        "value": "61576807138554%3AaGwvSIgmHa%2C61576614967012%3Ay6vtf9xvVs%2C61576873704000%3AFgMWbGzhoR%2C61579860272280%3Ap7iF84wHoc",
        "domain": "facebook.com",
        "path": "/",
        "hostOnly": false,
        "creation": "2025-08-29T10:48:30.000Z",
        "lastAccessed": "2025-08-29T10:48:30.000Z"
    },
    {
        "key": "dpr",
        "value": "2.75",
        "domain": "facebook.com",
        "path": "/",
        "hostOnly": false,
        "creation": "2025-08-29T10:48:30.000Z",
        "lastAccessed": "2025-08-29T10:48:30.000Z"
    },
    {
        "key": "locale",
        "value": "en_GB",
        "domain": "facebook.com",
        "path": "/",
        "hostOnly": false,
        "creation": "2025-08-29T10:48:30.000Z",
        "lastAccessed": "2025-08-29T10:48:30.000Z"
    },
    {
        "key": "m_pixel_ratio",
        "value": "2.75",
        "domain": "facebook.com",
        "path": "/",
        "hostOnly": false,
        "creation": "2025-08-29T10:48:30.001Z",
        "lastAccessed": "2025-08-29T10:48:30.001Z"
    },
    {
        "key": "wd",
        "value": "393x873",
        "domain": "facebook.com",
        "path": "/",
        "hostOnly": false,
        "creation": "2025-08-29T10:48:30.001Z",
        "lastAccessed": "2025-08-29T10:48:30.001Z"
    },
    {
        "key": "c_user",
        "value": "61579860272280",
        "domain": "facebook.com",
        "path": "/",
        "hostOnly": false,
        "creation": "2025-08-29T10:48:30.001Z",
        "lastAccessed": "2025-08-29T10:48:30.001Z"
    },
    {
        "key": "xs",
        "value": "26%3As3_txYWeCepnUg%3A2%3A1756464473%3A-1%3A-1",
        "domain": "facebook.com",
        "path": "/",
        "hostOnly": false,
        "creation": "2025-08-29T10:48:30.001Z",
        "lastAccessed": "2025-08-29T10:48:30.001Z"
    },
    {
        "key": "fr",
        "value": "0Jpks4B8jn0ebXULS.AWeRXLA2IdbWjPhrsAzBBhQfeLs1yN9k7OGzhTFUm9BgyJUIlho.Boqb6Q..AAA.0.0.BosYVc.AWfeaXI4Q1DmzvQ5mwsK8f23yig",
        "domain": "facebook.com",
        "path": "/",
        "hostOnly": false,
        "creation": "2025-08-29T10:48:30.001Z",
        "lastAccessed": "2025-08-29T10:48:30.001Z"
    },
    {
        "key": "fbl_st",
        "value": "101732339%3BT%3A29274407",
        "domain": "facebook.com",
        "path": "/",
        "hostOnly": false,
        "creation": "2025-08-29T10:48:30.001Z",
        "lastAccessed": "2025-08-29T10:48:30.001Z"
    },
    {
        "key": "wl_cbv",
        "value": "v2%3Bclient_version%3A2906%3Btimestamp%3A1756464476",
        "domain": "facebook.com",
        "path": "/",
        "hostOnly": false,
        "creation": "2025-08-29T10:48:30.001Z",
        "lastAccessed": "2025-08-29T10:48:30.001Z"
    }
]
