[
    {
        "key": "dbln",
        "value": "%7B%2261579860272280%22%3A%225mZGs8Wa%22%2C%2261580005887820%22%3A%22VellkmP6%22%7D",
        "domain": "facebook.com",
        "path": "/login/device-based/",
        "hostOnly": false,
        "creation": "2025-08-30T18:32:30.157Z",
        "lastAccessed": "2025-08-30T18:32:30.158Z"
    },
    {
        "key": "datr",
        "value": "StexaOZBHWKbpQIzWNwTPkuK",
        "domain": "facebook.com",
        "path": "/",
        "hostOnly": false,
        "creation": "2025-08-30T18:32:30.158Z",
        "lastAccessed": "2025-08-30T18:32:30.158Z"
    },
    {
        "key": "sb",
        "value": "StexaKQKeKWxkXxHelMChiVF",
        "domain": "facebook.com",
        "path": "/",
        "hostOnly": false,
        "creation": "2025-08-30T18:32:30.158Z",
        "lastAccessed": "2025-08-30T18:32:30.158Z"
    },
    {
        "key": "vpd",
        "value": "v1%3B767x393x2.75",
        "domain": "facebook.com",
        "path": "/",
        "hostOnly": false,
        "creation": "2025-08-30T18:32:30.158Z",
        "lastAccessed": "2025-08-30T18:32:30.158Z"
    },
    {
        "key": "ps_l",
        "value": "1",
        "domain": "facebook.com",
        "path": "/",
        "hostOnly": false,
        "creation": "2025-08-30T18:32:30.158Z",
        "lastAccessed": "2025-08-30T18:32:30.158Z"
    },
    {
        "key": "ps_n",
        "value": "1",
        "domain": "facebook.com",
        "path": "/",
        "hostOnly": false,
        "creation": "2025-08-30T18:32:30.158Z",
        "lastAccessed": "2025-08-30T18:32:30.158Z"
    },
    {
        "key": "m_pixel_ratio",
        "value": "2.75",
        "domain": "facebook.com",
        "path": "/",
        "hostOnly": false,
        "creation": "2025-08-30T18:32:30.158Z",
        "lastAccessed": "2025-08-30T18:32:30.158Z"
    },
    {
        "key": "wd",
        "value": "393x873",
        "domain": "facebook.com",
        "path": "/",
        "hostOnly": false,
        "creation": "2025-08-30T18:32:30.158Z",
        "lastAccessed": "2025-08-30T18:32:30.158Z"
    },
    {
        "key": "pas",
        "value": "61579860272280%3ADYWSmmCX62%2C61580005887820%3AEBJoy4sKjo",
        "domain": "facebook.com",
        "path": "/",
        "hostOnly": false,
        "creation": "2025-08-30T18:32:30.158Z",
        "lastAccessed": "2025-08-30T18:32:30.158Z"
    },
    {
        "key": "locale",
        "value": "bn_IN",
        "domain": "facebook.com",
        "path": "/",
        "hostOnly": false,
        "creation": "2025-08-30T18:32:30.158Z",
        "lastAccessed": "2025-08-30T18:32:30.158Z"
    },
    {
        "key": "c_user",
        "value": "61579860272280",
        "domain": "facebook.com",
        "path": "/",
        "hostOnly": false,
        "creation": "2025-08-30T18:32:30.158Z",
        "lastAccessed": "2025-08-30T18:32:30.158Z"
    },
    {
        "key": "xs",
        "value": "5%3AHnUBoUR7rzskUg%3A2%3A1756578738%3A-1%3A-1",
        "domain": "facebook.com",
        "path": "/",
        "hostOnly": false,
        "creation": "2025-08-30T18:32:30.158Z",
        "lastAccessed": "2025-08-30T18:32:30.158Z"
    },
    {
        "key": "fr",
        "value": "0syzhaPGaA7cxrPDu.AWfDacduCzo1UzQajoM2MXtCYvTxZzf7zaXqAlIgQEZcZHa45ss.BosddK..AAA.0.0.Bos0O0.AWe3RdG3jT0ebmrqwpBsxZgNZxI",
        "domain": "facebook.com",
        "path": "/",
        "hostOnly": false,
        "creation": "2025-08-30T18:32:30.158Z",
        "lastAccessed": "2025-08-30T18:32:30.158Z"
    },
    {
        "key": "wl_cbv",
        "value": "v2%3Bclient_version%3A2908%3Btimestamp%3A1756578741",
        "domain": "facebook.com",
        "path": "/",
        "hostOnly": false,
        "creation": "2025-08-30T18:32:30.158Z",
        "lastAccessed": "2025-08-30T18:32:30.158Z"
    },
    {
        "key": "fbl_st",
        "value": "101416471%3BT%3A29276312",
        "domain": "facebook.com",
        "path": "/",
        "hostOnly": false,
        "creation": "2025-08-30T18:32:30.158Z",
        "lastAccessed": "2025-08-30T18:32:30.158Z"
    }
        ]
